src/router.sv
module router (
  input logic clk,
  input logic rst_n,

  //The location of the router
  input logic[3:0] location,

  input logic[36:0] east_in,
  input logic[36:0] west_in,
  input logic[36:0] north_in,
  input logic[36:0] south_in,
  input logic[36:0] local_in,

  output logic[36:0] east_out,
  output logic[36:0] west_out,
  output logic[36:0] north_out,
  output logic[36:0] south_out,
  output logic[36:0] local_out
);

  //selects which input are assigned to an output
  //0XX -> the output should be 37'd0
  //1YY -> output is the input if address YY
  logic[2:0] selE;
  logic[2:0] selW;
  logic[2:0] selN;
  logic[2:0] selS;
  logic[2:0] selL;

  //Creating all registers and wiring them to their outputs
  logic[36:0] east_reg;
  logic[36:0] west_reg;
  logic[36:0] north_reg;
  logic[36:0] south_reg;
  logic[36:0] local_reg;
  assign east_out = east_reg;
  assign west_out = west_reg;
  assign north_out = north_reg;
  assign south_out = south_reg;
  assign local_out = local_reg;

  always_ff @(posedge clk) begin
    if(!rst_n) begin
      // Default
      east_reg <= 37'd0;
      west_reg <= 37'd0;
      north_reg <= 37'd0;
      south_reg <= 37'd0;
      local_reg <= 37'd0;

    end else begin
      // Default
      east_reg <= 37'd0;
      west_reg <= 37'd0;
      north_reg <= 37'd0;
      south_reg <= 37'd0;
      local_reg <= 37'd0;

      //  ***CHOOSING WHERE THE PACKAGES SHOULD MOVE***
      // determining which package moves east
      if(west_in[36] == 1'b1 && west_in[35:34] != 2'b00) begin
        if(west_in[33:32] > location[1:0]) begin
          east_reg <= west_in;
        end
      end else if(north_in[36] == 1'b1 && north_in[35:34] != 2'b00) begin
        if(north_in[33:32] > location[1:0]) begin
          east_reg <= north_in;
        end
      end else if(south_in[36] == 1'b1 && south_in[35:34] != 2'b00) begin
        if(south_in[33:32] > location[1:0]) begin
          east_reg <= south_in;
        end
      end else if(local_in[36] == 1'b1 && local_in[35:34] != 2'b00) begin
        if(local_in[33:32] > location[1:0]) begin
          east_reg <= local_in;
        end
      end
      // determining which package moves west
      if(east_in[36] == 1'b1 && east_in[35:34] != 2'b00) begin
        if(east_in[33:32] < location[1:0] && east_in[33:32] != 2'b00) begin
          west_reg <= east_in;
        end
      end else if(north_in[36] == 1'b1 && north_in[35:34] != 2'b00) begin
        if(north_in[33:32] < location[1:0] && north_in[33:32] != 2'b00) begin
          west_reg <= north_in;
        end
      end else if(south_in[36] == 1'b1 && south_in[35:34] != 2'b00) begin
        if(south_in[33:32] < location[1:0] && south_in[33:32] != 2'b00) begin
          west_reg <= south_in;
        end
      end else if(local_in[36] == 1'b1 && local_in[35:34] != 2'b00) begin
        if(local_in[33:32] < location[1:0] && local_in[33:32] != 2'b00) begin
          west_reg <= local_in;
        end
      end
      // determining which package moves north
      if(east_in[36] == 1'b1 && east_in[33:32] == location[1:0]) begin
        if(east_in[35:34] > location[3:2]) begin
          north_reg <= east_in;
        end
      end else if(west_in[36] == 1'b1 && west_in[33:32] == location[1:0]) begin
        if(west_in[35:34] > location[3:2]) begin
          north_reg <= west_in;
        end
      end else if(south_in[36] == 1'b1 && south_in[33:32] == location[1:0]) begin
        if(south_in[35:34] > location[3:2]) begin
          north_reg <= south_in;
        end
      end else if(local_in[36] == 1'b1 && local_in[33:32] == location[1:0]) begin
        if(local_in[35:34] > location[3:2]) begin
          north_reg <= local_in;
        end
      end
      // determining which package moves south
      if(east_in[36] == 1'b1 && east_in[33:32] == location[1:0]) begin
        if(east_in[35:34] < location[3:2] && east_in[33:32] != 2'b00) begin
          south_reg <= east_in;
        end
      end else if(west_in[36] == 1'b1 && west_in[33:32] == location[1:0]) begin
        if(west_in[35:34] < location[3:2] && east_in[33:32] != 2'b00) begin
          south_reg <= west_in;
        end
      end else if(north_in[36] == 1'b1 && north_in[33:32] == location[1:0]) begin
        if(north_in[35:34] < location[3:2] && east_in[33:32] != 2'b00) begin
          south_reg <= north_in;
        end
      end else if(local_in[36] == 1'b1 && local_in[33:32] == location[1:0]) begin
        if(local_in[35:34] < location[3:2] && east_in[33:32] != 2'b00) begin
          south_reg <= local_in;
        end
      end
      // determining which package moves local
      if(west_in[36] == 1'b1) begin
        if(west_in[35:32] == location[3:0]) begin
          local_reg <= west_in;
        end
      end else if(east_in[36] == 1'b1) begin
        if(east_in[35:32] == location[3:0]) begin
          local_reg <= east_in;
        end
      end else if(north_in[36] == 1'b1) begin
        if(north_in[35:32] == location[3:0]) begin
          local_reg <= north_in;
        end
      end else if(south_in[36] == 1'b1) begin
        if(south_in[35:32] == location[3:0]) begin
          local_reg <= south_in;
        end
      end
    end
  end


endmodule

src/noc_top.sv
// top module for 3x3 torus-connected routers

module noc_top (
  input  logic        clk,
  input  logic        rst_n,

  // inputs
  input  logic [36:0] local_in_a,
  input  logic [36:0] local_in_b,
  input  logic [36:0] local_in_c,
  input  logic [36:0] local_in_d,
  input  logic [36:0] local_in_e,
  input  logic [36:0] local_in_f,
  input  logic [36:0] local_in_g,
  input  logic [36:0] local_in_h,
  input  logic [36:0] local_in_i,

  // outputs
  output logic [36:0] local_out_a,
  output logic [36:0] local_out_b,
  output logic [36:0] local_out_c,
  output logic [36:0] local_out_d,
  output logic [36:0] local_out_e,
  output logic [36:0] local_out_f,
  output logic [36:0] local_out_g,
  output logic [36:0] local_out_h,
  output logic [36:0] local_out_i
);

  // row rings
  logic [36:0] a_b_e, b_c_e, c_a_e;      // row y=01 east
  logic [36:0] b_a_w, c_b_w, a_c_w;      // row y=01 west
  logic [36:0] d_e_e, e_f_e, f_d_e;      // row y=10 east
  logic [36:0] e_d_w, f_e_w, d_f_w;      // row y=10 west
  logic [36:0] g_h_e, h_i_e, i_g_e;      // row y=11 east
  logic [36:0] h_g_w, i_h_w, g_i_w;      // row y=11 west

  // column rings
  logic [36:0] a_d_s, d_g_s, g_a_s;      // column x=01 south
  logic [36:0] d_a_n, g_d_n, a_g_n;      // column x=01 north
  logic [36:0] b_e_s, e_h_s, h_b_s;      // column x=10 south
  logic [36:0] e_b_n, h_e_n, b_h_n;      // column x=10 north
  logic [36:0] c_f_s, f_i_s, i_c_s;      // column x=11 south
  logic [36:0] f_c_n, i_f_n, c_i_n;      // column x=11 north


  // A, location 0101. East B, west C, south D, north G
  router u_a (
    .clk       (clk),
    .rst_n     (rst_n),
    .location  (4'b01_01),
    .east_in   (b_a_w),
    .west_in   (c_a_e),
    .north_in  (g_a_s),
    .south_in  (d_a_n),
    .local_in  (local_in_a),
    .east_out  (a_b_e),
    .west_out  (a_c_w),
    .north_out (a_g_n),
    .south_out (a_d_s),
    .local_out (local_out_a)
  );

  // B, location 0110. East C, west A, south E, north H
  router u_b (
    .clk       (clk),
    .rst_n     (rst_n),
    .location  (4'b01_10),
    .east_in   (c_b_w),
    .west_in   (a_b_e),
    .north_in  (h_b_s),
    .south_in  (e_b_n),
    .local_in  (local_in_b),
    .east_out  (b_c_e),
    .west_out  (b_a_w),
    .north_out (b_h_n),
    .south_out (b_e_s),
    .local_out (local_out_b)
  );

  // C, location 0111. East A , west B, south F, north I
  router u_c (
    .clk       (clk),
    .rst_n     (rst_n),
    .location  (4'b01_11),
    .east_in   (a_c_w),
    .west_in   (b_c_e),
    .north_in  (i_c_s),
    .south_in  (f_c_n),
    .local_in  (local_in_c),
    .east_out  (c_a_e),
    .west_out  (c_b_w),
    .north_out (c_i_n),
    .south_out (c_f_s),
    .local_out (local_out_c)
  );

  // D, location 1001. east E, west F , south G, north A 
  router u_d (
    .clk       (clk),
    .rst_n     (rst_n),
    .location  (4'b10_01),
    .east_in   (e_d_w),
    .west_in   (f_d_e),
    .north_in  (a_d_s),
    .south_in  (g_d_n),
    .local_in  (local_in_d),
    .east_out  (d_e_e),
    .west_out  (d_f_w),
    .north_out (d_a_n),
    .south_out (d_g_s),
    .local_out (local_out_d)
  );

  // E, centre, location 1010. east F, west D, south H, north B 
  router u_e (
    .clk       (clk),
    .rst_n     (rst_n),
    .location  (4'b10_10),
    .east_in   (f_e_w),
    .west_in   (d_e_e),
    .north_in  (b_e_s),
    .south_in  (h_e_n),
    .local_in  (local_in_e),
    .east_out  (e_f_e),
    .west_out  (e_d_w),
    .north_out (e_b_n),
    .south_out (e_h_s),
    .local_out (local_out_e)
  );

  //  F, location 1011. east D , west E, south I, north C 
  router u_f (
    .clk       (clk),
    .rst_n     (rst_n),
    .location  (4'b10_11),
    .east_in   (d_f_w),
    .west_in   (e_f_e),
    .north_in  (c_f_s),
    .south_in  (i_f_n),
    .local_in  (local_in_f),
    .east_out  (f_d_e),
    .west_out  (f_e_w),
    .north_out (f_c_n),
    .south_out (f_i_s),
    .local_out (local_out_f)
  );

  // G, location 1101. east H, west I , south A , north D 
  router u_g (
    .clk       (clk),
    .rst_n     (rst_n),
    .location  (4'b11_01),
    .east_in   (h_g_w),
    .west_in   (i_g_e),
    .north_in  (d_g_s),
    .south_in  (a_g_n),
    .local_in  (local_in_g),
    .east_out  (g_h_e),
    .west_out  (g_i_w),
    .north_out (g_d_n),
    .south_out (g_a_s),
    .local_out (local_out_g)
  );

  // H, location 1110. east I, west G, south B , north E 
  router u_h (
    .clk       (clk),
    .rst_n     (rst_n),
    .location  (4'b11_10),
    .east_in   (i_h_w),
    .west_in   (g_h_e),
    .north_in  (e_h_s),
    .south_in  (b_h_n),
    .local_in  (local_in_h),
    .east_out  (h_i_e),
    .west_out  (h_g_w),
    .north_out (h_e_n),
    .south_out (h_b_s),
    .local_out (local_out_h)
  );

  // I, location 1111. east G , west H, south C , north F 
  router u_i (
    .clk       (clk),
    .rst_n     (rst_n),
    .location  (4'b11_11),
    .east_in   (g_i_w),
    .west_in   (h_i_e),
    .north_in  (f_i_s),
    .south_in  (c_i_n),
    .local_in  (local_in_i),
    .east_out  (i_g_e),
    .west_out  (i_h_w),
    .north_out (i_f_n),
    .south_out (i_c_s),
    .local_out (local_out_i)
  );

endmodule

tb/noc_top_tb.sv
`timescale 1ns/1ns

module noc_top_tb ;
logic clk, rst_n;
logic[36:0] local_in_a, local_in_b, local_in_c, local_in_d, local_in_e;
logic[36:0] local_in_f, local_in_g, local_in_h, local_in_i;
logic[36:0] local_out_a, local_out_b, local_out_c, local_out_d, local_out_e;
logic[36:0] local_out_f, local_out_g, local_out_h, local_out_i;

noc_top dut(
  .clk(clk),
  .rst_n(rst_n),
  .local_in_a(local_in_a),
  .local_in_b(local_in_b),
  .local_in_c(local_in_c),
  .local_in_d(local_in_d),
  .local_in_e(local_in_e),
  .local_in_f(local_in_f),
  .local_in_g(local_in_g),
  .local_in_h(local_in_h),
  .local_in_i(local_in_i),
  .local_out_a(local_out_a),
  .local_out_b(local_out_b),
  .local_out_c(local_out_c),
  .local_out_d(local_out_d),
  .local_out_e(local_out_e),
  .local_out_f(local_out_f),
  .local_out_g(local_out_g),
  .local_out_h(local_out_h),
  .local_out_i(local_out_i)
);

initial begin
  $dumpfile("noc_top_tb.vcd");
  $dumpvars(0, noc_top_tb);
end

initial begin
  clk = 0;
  forever #5 clk = ~clk;
end

// Small task to just print all the input and output values
task automatic print_input_and_output();
  $display("Time=%0t   a=%b b=%b c=%b d=%b e=%b f=%b g=%b h=%b i=%b | a=%b b=%b c=%b d=%b e=%b f=%b g=%b h=%b i=%b",
            $time,
            local_in_a[36:32], local_in_b[36:32], local_in_c[36:32],
            local_in_d[36:32], local_in_e[36:32], local_in_f[36:32],
            local_in_g[36:32], local_in_h[36:32], local_in_i[36:32],
            local_out_a[36:32], local_out_b[36:32], local_out_c[36:32],
            local_out_d[36:32], local_out_e[36:32], local_out_f[36:32],
            local_out_g[36:32], local_out_h[36:32], local_out_i[36:32]);
endtask


initial begin
  //Setting the initial value of all inputs
  local_in_a = '0;
  local_in_b = '0;
  local_in_c = '0;
  local_in_d = '0;
  local_in_e = '0;
  local_in_f = '0;
  local_in_g = '0;
  local_in_h = '0;
  local_in_i = '0;

  //restarting the module
  rst_n = 0;
  repeat (2) @(posedge clk);  // hold reset across at least one full edge
  rst_n = 1;
  @(posedge clk);
  #1;

  local_in_a = 37'b1111100000000000000000000000000000000;
  #10;
  print_input_and_output();
  @(posedge clk);
  local_in_a = 37'b0000000000000000000000000000000000000;
  #1;
  print_input_and_output();
  @(posedge clk);
  print_input_and_output();
  @(posedge clk);
  print_input_and_output();
  @(posedge clk);
  print_input_and_output();
  @(posedge clk);
  print_input_and_output();
  @(posedge clk);
  print_input_and_output();
  @(posedge clk);
  print_input_and_output();
  @(posedge clk);



  $finish;

end

endmodule

noc_top_tb.vcd
$date
	Wed Aug 26 12:11:44 2026
$end
$version
	Icarus Verilog
$end
$timescale
	1ns
$end
$scope module noc_top_tb $end
$var wire 37 ! local_out_i [36:0] $end
$var wire 37 " local_out_h [36:0] $end
$var wire 37 # local_out_g [36:0] $end
$var wire 37 $ local_out_f [36:0] $end
$var wire 37 % local_out_e [36:0] $end
$var wire 37 & local_out_d [36:0] $end
$var wire 37 ' local_out_c [36:0] $end
$var wire 37 ( local_out_b [36:0] $end
$var wire 37 ) local_out_a [36:0] $end
$var reg 1 * clk $end
$var reg 37 + local_in_a [36:0] $end
$var reg 37 , local_in_b [36:0] $end
$var reg 37 - local_in_c [36:0] $end
$var reg 37 . local_in_d [36:0] $end
$var reg 37 / local_in_e [36:0] $end
$var reg 37 0 local_in_f [36:0] $end
$var reg 37 1 local_in_g [36:0] $end
$var reg 37 2 local_in_h [36:0] $end
$var reg 37 3 local_in_i [36:0] $end
$var reg 1 4 rst_n $end
$scope module dut $end
$var wire 1 * clk $end
$var wire 37 5 local_in_a [36:0] $end
$var wire 37 6 local_in_b [36:0] $end
$var wire 37 7 local_in_c [36:0] $end
$var wire 37 8 local_in_d [36:0] $end
$var wire 37 9 local_in_e [36:0] $end
$var wire 37 : local_in_f [36:0] $end
$var wire 37 ; local_in_g [36:0] $end
$var wire 37 < local_in_h [36:0] $end
$var wire 37 = local_in_i [36:0] $end
$var wire 1 4 rst_n $end
$var wire 37 > local_out_i [36:0] $end
$var wire 37 ? local_out_h [36:0] $end
$var wire 37 @ local_out_g [36:0] $end
$var wire 37 A local_out_f [36:0] $end
$var wire 37 B local_out_e [36:0] $end
$var wire 37 C local_out_d [36:0] $end
$var wire 37 D local_out_c [36:0] $end
$var wire 37 E local_out_b [36:0] $end
$var wire 37 F local_out_a [36:0] $end
$var wire 37 G i_h_w [36:0] $end
$var wire 37 H i_g_e [36:0] $end
$var wire 37 I i_f_n [36:0] $end
$var wire 37 J i_c_s [36:0] $end
$var wire 37 K h_i_e [36:0] $end
$var wire 37 L h_g_w [36:0] $end
$var wire 37 M h_e_n [36:0] $end
$var wire 37 N h_b_s [36:0] $end
$var wire 37 O g_i_w [36:0] $end
$var wire 37 P g_h_e [36:0] $end
$var wire 37 Q g_d_n [36:0] $end
$var wire 37 R g_a_s [36:0] $end
$var wire 37 S f_i_s [36:0] $end
$var wire 37 T f_e_w [36:0] $end
$var wire 37 U f_d_e [36:0] $end
$var wire 37 V f_c_n [36:0] $end
$var wire 37 W e_h_s [36:0] $end
$var wire 37 X e_f_e [36:0] $end
$var wire 37 Y e_d_w [36:0] $end
$var wire 37 Z e_b_n [36:0] $end
$var wire 37 [ d_g_s [36:0] $end
$var wire 37 \ d_f_w [36:0] $end
$var wire 37 ] d_e_e [36:0] $end
$var wire 37 ^ d_a_n [36:0] $end
$var wire 37 _ c_i_n [36:0] $end
$var wire 37 ` c_f_s [36:0] $end
$var wire 37 a c_b_w [36:0] $end
$var wire 37 b c_a_e [36:0] $end
$var wire 37 c b_h_n [36:0] $end
$var wire 37 d b_e_s [36:0] $end
$var wire 37 e b_c_e [36:0] $end
$var wire 37 f b_a_w [36:0] $end
$var wire 37 g a_g_n [36:0] $end
$var wire 37 h a_d_s [36:0] $end
$var wire 37 i a_c_w [36:0] $end
$var wire 37 j a_b_e [36:0] $end
$scope module u_a $end
$var wire 1 * clk $end
$var wire 37 k east_out [36:0] $end
$var wire 37 l local_in [36:0] $end
$var wire 37 m local_out [36:0] $end
$var wire 4 n location [3:0] $end
$var wire 37 o north_out [36:0] $end
$var wire 1 4 rst_n $end
$var wire 37 p south_out [36:0] $end
$var wire 37 q west_out [36:0] $end
$var wire 37 r west_in [36:0] $end
$var wire 37 s south_in [36:0] $end
$var wire 37 t north_in [36:0] $end
$var wire 37 u east_in [36:0] $end
$var reg 37 v east_reg [36:0] $end
$var reg 37 w local_reg [36:0] $end
$var reg 37 x north_reg [36:0] $end
$var reg 37 y south_reg [36:0] $end
$var reg 37 z west_reg [36:0] $end
$upscope $end
$scope module u_b $end
$var wire 1 * clk $end
$var wire 37 { east_out [36:0] $end
$var wire 37 | local_in [36:0] $end
$var wire 37 } local_out [36:0] $end
$var wire 4 ~ location [3:0] $end
$var wire 37 !" north_out [36:0] $end
$var wire 1 4 rst_n $end
$var wire 37 "" south_out [36:0] $end
$var wire 37 #" west_in [36:0] $end
$var wire 37 $" west_out [36:0] $end
$var wire 37 %" south_in [36:0] $end
$var wire 37 &" north_in [36:0] $end
$var wire 37 '" east_in [36:0] $end
$var reg 37 (" east_reg [36:0] $end
$var reg 37 )" local_reg [36:0] $end
$var reg 37 *" north_reg [36:0] $end
$var reg 37 +" south_reg [36:0] $end
$var reg 37 ," west_reg [36:0] $end
$upscope $end
$scope module u_c $end
$var wire 1 * clk $end
$var wire 37 -" east_in [36:0] $end
$var wire 37 ." east_out [36:0] $end
$var wire 37 /" local_in [36:0] $end
$var wire 37 0" local_out [36:0] $end
$var wire 4 1" location [3:0] $end
$var wire 37 2" north_out [36:0] $end
$var wire 1 4 rst_n $end
$var wire 37 3" south_out [36:0] $end
$var wire 37 4" west_in [36:0] $end
$var wire 37 5" west_out [36:0] $end
$var wire 37 6" south_in [36:0] $end
$var wire 37 7" north_in [36:0] $end
$var reg 37 8" east_reg [36:0] $end
$var reg 37 9" local_reg [36:0] $end
$var reg 37 :" north_reg [36:0] $end
$var reg 37 ;" south_reg [36:0] $end
$var reg 37 <" west_reg [36:0] $end
$upscope $end
$scope module u_d $end
$var wire 1 * clk $end
$var wire 37 =" east_out [36:0] $end
$var wire 37 >" local_in [36:0] $end
$var wire 37 ?" local_out [36:0] $end
$var wire 4 @" location [3:0] $end
$var wire 37 A" north_in [36:0] $end
$var wire 37 B" north_out [36:0] $end
$var wire 1 4 rst_n $end
$var wire 37 C" south_out [36:0] $end
$var wire 37 D" west_out [36:0] $end
$var wire 37 E" west_in [36:0] $end
$var wire 37 F" south_in [36:0] $end
$var wire 37 G" east_in [36:0] $end
$var reg 37 H" east_reg [36:0] $end
$var reg 37 I" local_reg [36:0] $end
$var reg 37 J" north_reg [36:0] $end
$var reg 37 K" south_reg [36:0] $end
$var reg 37 L" west_reg [36:0] $end
$upscope $end
$scope module u_e $end
$var wire 1 * clk $end
$var wire 37 M" east_out [36:0] $end
$var wire 37 N" local_in [36:0] $end
$var wire 37 O" local_out [36:0] $end
$var wire 4 P" location [3:0] $end
$var wire 37 Q" north_in [36:0] $end
$var wire 37 R" north_out [36:0] $end
$var wire 1 4 rst_n $end
$var wire 37 S" south_out [36:0] $end
$var wire 37 T" west_in [36:0] $end
$var wire 37 U" west_out [36:0] $end
$var wire 37 V" south_in [36:0] $end
$var wire 37 W" east_in [36:0] $end
$var reg 37 X" east_reg [36:0] $end
$var reg 37 Y" local_reg [36:0] $end
$var reg 37 Z" north_reg [36:0] $end
$var reg 37 [" south_reg [36:0] $end
$var reg 37 \" west_reg [36:0] $end
$upscope $end
$scope module u_f $end
$var wire 1 * clk $end
$var wire 37 ]" east_in [36:0] $end
$var wire 37 ^" east_out [36:0] $end
$var wire 37 _" local_in [36:0] $end
$var wire 37 `" local_out [36:0] $end
$var wire 4 a" location [3:0] $end
$var wire 37 b" north_in [36:0] $end
$var wire 37 c" north_out [36:0] $end
$var wire 1 4 rst_n $end
$var wire 37 d" south_out [36:0] $end
$var wire 37 e" west_in [36:0] $end
$var wire 37 f" west_out [36:0] $end
$var wire 37 g" south_in [36:0] $end
$var reg 37 h" east_reg [36:0] $end
$var reg 37 i" local_reg [36:0] $end
$var reg 37 j" north_reg [36:0] $end
$var reg 37 k" south_reg [36:0] $end
$var reg 37 l" west_reg [36:0] $end
$upscope $end
$scope module u_g $end
$var wire 1 * clk $end
$var wire 37 m" east_out [36:0] $end
$var wire 37 n" local_in [36:0] $end
$var wire 37 o" local_out [36:0] $end
$var wire 4 p" location [3:0] $end
$var wire 37 q" north_in [36:0] $end
$var wire 37 r" north_out [36:0] $end
$var wire 1 4 rst_n $end
$var wire 37 s" south_in [36:0] $end
$var wire 37 t" south_out [36:0] $end
$var wire 37 u" west_out [36:0] $end
$var wire 37 v" west_in [36:0] $end
$var wire 37 w" east_in [36:0] $end
$var reg 37 x" east_reg [36:0] $end
$var reg 37 y" local_reg [36:0] $end
$var reg 37 z" north_reg [36:0] $end
$var reg 37 {" south_reg [36:0] $end
$var reg 37 |" west_reg [36:0] $end
$upscope $end
$scope module u_h $end
$var wire 1 * clk $end
$var wire 37 }" east_out [36:0] $end
$var wire 37 ~" local_in [36:0] $end
$var wire 37 !# local_out [36:0] $end
$var wire 4 "# location [3:0] $end
$var wire 37 ## north_in [36:0] $end
$var wire 37 $# north_out [36:0] $end
$var wire 1 4 rst_n $end
$var wire 37 %# south_in [36:0] $end
$var wire 37 &# south_out [36:0] $end
$var wire 37 '# west_in [36:0] $end
$var wire 37 (# west_out [36:0] $end
$var wire 37 )# east_in [36:0] $end
$var reg 37 *# east_reg [36:0] $end
$var reg 37 +# local_reg [36:0] $end
$var reg 37 ,# north_reg [36:0] $end
$var reg 37 -# south_reg [36:0] $end
$var reg 37 .# west_reg [36:0] $end
$upscope $end
$scope module u_i $end
$var wire 1 * clk $end
$var wire 37 /# east_in [36:0] $end
$var wire 37 0# east_out [36:0] $end
$var wire 37 1# local_in [36:0] $end
$var wire 37 2# local_out [36:0] $end
$var wire 4 3# location [3:0] $end
$var wire 37 4# north_in [36:0] $end
$var wire 37 5# north_out [36:0] $end
$var wire 1 4 rst_n $end
$var wire 37 6# south_in [36:0] $end
$var wire 37 7# south_out [36:0] $end
$var wire 37 8# west_in [36:0] $end
$var wire 37 9# west_out [36:0] $end
$var reg 37 :# east_reg [36:0] $end
$var reg 37 ;# local_reg [36:0] $end
$var reg 37 <# north_reg [36:0] $end
$var reg 37 =# south_reg [36:0] $end
$var reg 37 ># west_reg [36:0] $end
$upscope $end
$upscope $end
$scope task print_input_and_output $end
$upscope $end
$upscope $end
$enddefinitions $end
$comment Show the parameter values. $end
$dumpall
$end
#0
$dumpvars
bx >#
bx =#
bx <#
bx ;#
bx :#
bx 9#
bx 8#
bx 7#
bx 6#
bx 5#
bx 4#
b1111 3#
bx 2#
b0 1#
bx 0#
bx /#
bx .#
bx -#
bx ,#
bx +#
bx *#
bx )#
bx (#
bx '#
bx &#
bx %#
bx $#
bx ##
b1110 "#
bx !#
b0 ~"
bx }"
bx |"
bx {"
bx z"
bx y"
bx x"
bx w"
bx v"
bx u"
bx t"
bx s"
bx r"
bx q"
b1101 p"
bx o"
b0 n"
bx m"
bx l"
bx k"
bx j"
bx i"
bx h"
bx g"
bx f"
bx e"
bx d"
bx c"
bx b"
b1011 a"
bx `"
b0 _"
bx ^"
bx ]"
bx \"
bx ["
bx Z"
bx Y"
bx X"
bx W"
bx V"
bx U"
bx T"
bx S"
bx R"
bx Q"
b1010 P"
bx O"
b0 N"
bx M"
bx L"
bx K"
bx J"
bx I"
bx H"
bx G"
bx F"
bx E"
bx D"
bx C"
bx B"
bx A"
b1001 @"
bx ?"
b0 >"
bx ="
bx <"
bx ;"
bx :"
bx 9"
bx 8"
bx 7"
bx 6"
bx 5"
bx 4"
bx 3"
bx 2"
b111 1"
bx 0"
b0 /"
bx ."
bx -"
bx ,"
bx +"
bx *"
bx )"
bx ("
bx '"
bx &"
bx %"
bx $"
bx #"
bx ""
bx !"
b110 ~
bx }
b0 |
bx {
bx z
bx y
bx x
bx w
bx v
bx u
bx t
bx s
bx r
bx q
bx p
bx o
b101 n
bx m
b0 l
bx k
bx j
bx i
bx h
bx g
bx f
bx e
bx d
bx c
bx b
bx a
bx `
bx _
bx ^
bx ]
bx \
bx [
bx Z
bx Y
bx X
bx W
bx V
bx U
bx T
bx S
bx R
bx Q
bx P
bx O
bx N
bx M
bx L
bx K
bx J
bx I
bx H
bx G
bx F
bx E
bx D
bx C
bx B
bx A
bx @
bx ?
bx >
b0 =
b0 <
b0 ;
b0 :
b0 9
b0 8
b0 7
b0 6
b0 5
04
b0 3
b0 2
b0 1
b0 0
b0 /
b0 .
b0 -
b0 ,
b0 +
0*
bx )
bx (
bx '
bx &
bx %
bx $
bx #
bx "
bx !
$end
#5
b0 )
b0 F
b0 m
b0 w
b0 h
b0 p
b0 A"
b0 y
b0 g
b0 o
b0 s"
b0 x
b0 i
b0 q
b0 -"
b0 z
b0 j
b0 k
b0 #"
b0 v
b0 (
b0 E
b0 }
b0 )"
b0 d
b0 ""
b0 Q"
b0 +"
b0 c
b0 !"
b0 %#
b0 *"
b0 f
b0 u
b0 $"
b0 ,"
b0 e
b0 {
b0 4"
b0 ("
b0 '
b0 D
b0 0"
b0 9"
b0 `
b0 3"
b0 b"
b0 ;"
b0 _
b0 2"
b0 6#
b0 :"
b0 a
b0 '"
b0 5"
b0 <"
b0 b
b0 r
b0 ."
b0 8"
b0 &
b0 C
b0 ?"
b0 I"
b0 [
b0 C"
b0 q"
b0 K"
b0 ^
b0 s
b0 B"
b0 J"
b0 \
b0 D"
b0 ]"
b0 L"
b0 ]
b0 ="
b0 T"
b0 H"
b0 %
b0 B
b0 O"
b0 Y"
b0 W
b0 S"
b0 ##
b0 ["
b0 Z
b0 %"
b0 R"
b0 Z"
b0 Y
b0 G"
b0 U"
b0 \"
b0 X
b0 M"
b0 e"
b0 X"
b0 $
b0 A
b0 `"
b0 i"
b0 S
b0 d"
b0 4#
b0 k"
b0 V
b0 6"
b0 c"
b0 j"
b0 T
b0 W"
b0 f"
b0 l"
b0 U
b0 E"
b0 ^"
b0 h"
b0 #
b0 @
b0 o"
b0 y"
b0 R
b0 t
b0 t"
b0 {"
b0 Q
b0 F"
b0 r"
b0 z"
b0 O
b0 u"
b0 /#
b0 |"
b0 P
b0 m"
b0 '#
b0 x"
b0 "
b0 ?
b0 !#
b0 +#
b0 N
b0 &"
b0 &#
b0 -#
b0 M
b0 V"
b0 $#
b0 ,#
b0 L
b0 w"
b0 (#
b0 .#
b0 K
b0 }"
b0 8#
b0 *#
b0 !
b0 >
b0 2#
b0 ;#
b0 J
b0 7"
b0 7#
b0 =#
b0 I
b0 g"
b0 5#
b0 <#
b0 G
b0 )#
b0 9#
b0 >#
b0 H
b0 v"
b0 0#
b0 :#
1*
#10
0*
#15
14
1*
#20
0*
#25
1*
#26
b1111100000000000000000000000000000000 +
b1111100000000000000000000000000000000 5
b1111100000000000000000000000000000000 l
#30
0*
#35
b1111100000000000000000000000000000000 j
b1111100000000000000000000000000000000 k
b1111100000000000000000000000000000000 #"
b1111100000000000000000000000000000000 v
1*
#40
0*
#45
b0 j
b0 k
b0 #"
b0 v
b1111100000000000000000000000000000000 e
b1111100000000000000000000000000000000 {
b1111100000000000000000000000000000000 4"
b1111100000000000000000000000000000000 ("
b0 +
b0 5
b0 l
1*
#50
0*
#55
b1111100000000000000000000000000000000 _
b1111100000000000000000000000000000000 2"
b1111100000000000000000000000000000000 6#
b1111100000000000000000000000000000000 :"
b0 e
b0 {
b0 4"
b0 ("
1*
#60
0*
#65
b0 _
b0 2"
b0 6#
b0 :"
b1111100000000000000000000000000000000 !
b1111100000000000000000000000000000000 >
b1111100000000000000000000000000000000 2#
b1111100000000000000000000000000000000 ;#
1*
#70
0*
#75
b0 !
b0 >
b0 2#
b0 ;#
1*
