src/router.sv
module router (
  input logic clk,
  input logic rst_n,

  //The location of the router
  input logic[3:0] location,

  input logic[36:0] east_in,
  input logic[36:0] west_in,
  input logic[36:0] north_in,
  input logic[36:0] south_in,
  input logic[36:0] local_in,

  output logic[36:0] east_out,
  output logic[36:0] west_out,
  output logic[36:0] north_out,
  output logic[36:0] south_out,
  output logic[36:0] local_out
);

  //selects which input are assigned to an output
  //0XX -> the output should be 37'd0
  //1YY -> output is the input if address YY
  logic[2:0] selE;
  logic[2:0] selW;
  logic[2:0] selN;
  logic[2:0] selS;
  logic[2:0] selL;

  //Creating all registers and wiring them to their outputs
  logic[36:0] east_reg;
  logic[36:0] west_reg;
  logic[36:0] north_reg;
  logic[36:0] south_reg;
  logic[36:0] local_reg;
  assign east_out = east_reg;
  assign west_out = west_reg;
  assign north_out = north_reg;
  assign south_out = south_reg;
  assign local_out = local_reg;

  always_ff @(posedge clk) begin
    if(!rst_n) begin
      // Default
      east_reg <= 37'd0;
      west_reg <= 37'd0;
      north_reg <= 37'd0;
      south_reg <= 37'd0;
      local_reg <= 37'd0;

    end else begin
      // Default
      east_reg <= 37'd0;
      west_reg <= 37'd0;
      north_reg <= 37'd0;
      south_reg <= 37'd0;
      local_reg <= 37'd0;

      //  ***CHOOSING WHERE THE PACKAGES SHOULD MOVE***
      // determining which package moves east
      if(west_in[36] == 1'b1 && west_in[35:34] != 2'b00) begin
        if(west_in[33:32] > location[1:0]) begin
          east_reg <= west_in;
        end
      end else if(north_in[36] == 1'b1 && north_in[35:34] != 2'b00) begin
        if(north_in[33:32] > location[1:0]) begin
          east_reg <= north_in;
        end
      end else if(south_in[36] == 1'b1 && south_in[35:34] != 2'b00) begin
        if(south_in[33:32] > location[1:0]) begin
          east_reg <= south_in;
        end
      end else if(local_in[36] == 1'b1 && local_in[35:34] != 2'b00) begin
        if(local_in[33:32] > location[1:0]) begin
          east_reg <= local_in;
        end
      end
      // determining which package moves west
      if(east_in[36] == 1'b1 && east_in[35:34] != 2'b00) begin
        if(east_in[33:32] < location[1:0] && east_in[33:32] != 2'b00) begin
          west_reg <= east_in;
        end
      end else if(north_in[36] == 1'b1 && north_in[35:34] != 2'b00) begin
        if(north_in[33:32] < location[1:0] && north_in[33:32] != 2'b00) begin
          west_reg <= north_in;
        end
      end else if(south_in[36] == 1'b1 && south_in[35:34] != 2'b00) begin
        if(south_in[33:32] < location[1:0] && south_in[33:32] != 2'b00) begin
          west_reg <= south_in;
        end
      end else if(local_in[36] == 1'b1 && local_in[35:34] != 2'b00) begin
        if(local_in[33:32] < location[1:0] && local_in[33:32] != 2'b00) begin
          west_reg <= local_in;
        end
      end
      // determining which package moves north
      if(east_in[36] == 1'b1 && east_in[33:32] == location[1:0]) begin
        if(east_in[35:34] > location[3:2]) begin
          north_reg <= east_in;
        end
      end else if(west_in[36] == 1'b1 && west_in[33:32] == location[1:0]) begin
        if(west_in[35:34] > location[3:2]) begin
          north_reg <= west_in;
        end
      end else if(south_in[36] == 1'b1 && south_in[33:32] == location[1:0]) begin
        if(south_in[35:34] > location[3:2]) begin
          north_reg <= south_in;
        end
      end else if(local_in[36] == 1'b1 && local_in[33:32] == location[1:0]) begin
        if(local_in[35:34] > location[3:2]) begin
          north_reg <= local_in;
        end
      end
      // determining which package moves south
      if(east_in[36] == 1'b1 && east_in[33:32] == location[1:0]) begin
        if(east_in[35:34] < location[3:2] && east_in[33:32] != 2'b00) begin
          south_reg <= east_in;
        end
      end else if(west_in[36] == 1'b1 && west_in[33:32] == location[1:0]) begin
        if(west_in[35:34] < location[3:2] && east_in[33:32] != 2'b00) begin
          south_reg <= west_in;
        end
      end else if(north_in[36] == 1'b1 && north_in[33:32] == location[1:0]) begin
        if(north_in[35:34] < location[3:2] && east_in[33:32] != 2'b00) begin
          south_reg <= north_in;
        end
      end else if(local_in[36] == 1'b1 && local_in[33:32] == location[1:0]) begin
        if(local_in[35:34] < location[3:2] && east_in[33:32] != 2'b00) begin
          south_reg <= local_in;
        end
      end
      // determining which package moves local
      if(west_in[36] == 1'b1) begin
        if(west_in[35:32] == location[3:0]) begin
          local_reg <= west_in;
        end
      end else if(east_in[36] == 1'b1) begin
        if(east_in[35:32] == location[3:0]) begin
          local_reg <= east_in;
        end
      end else if(north_in[36] == 1'b1) begin
        if(north_in[35:32] == location[3:0]) begin
          local_reg <= north_in;
        end
      end else if(south_in[36] == 1'b1) begin
        if(south_in[35:32] == location[3:0]) begin
          local_reg <= south_in;
        end
      end
    end
  end


endmodule

tb/router_tb.sv
`timescale 1ns/1ps

module router_tb ;
logic clk, rst_n;
logic[3:0] location;
logic[36:0] east_in, west_in, north_in, south_in, local_in;
logic[36:0] east_out, west_out, north_out, south_out, local_out;

router dut(
  .clk(clk),
  .rst_n(rst_n),
  .location(location),
  .east_in(east_in),
  .west_in(west_in),
  .north_in(north_in),
  .south_in(south_in),
  .local_in(local_in),
  .east_out(east_out),
  .west_out(west_out),
  .north_out(north_out),
  .south_out(south_out),
  .local_out(local_out)
);

initial begin
  $dumpfile("router_tb.vcd");
  $dumpvars(0, router_tb);
end

initial begin
  clk = 0;
  forever #5 clk = ~clk;
end

// port enum for helper task
typedef enum { EAST, WEST, NORTH, SOUTH, LOCAL } port_e;

// Helper task: drive local_in, wait one clock for the register to update,
// then print the result
task automatic drive_and_print(input port_e port, input logic[36:0] val);

  // reset all inputs to 0 first so only the selected port carries traffic
  east_in  = '0;
  west_in  = '0;
  north_in = '0;
  south_in = '0;
  local_in = '0;

  case(port)
    EAST:  east_in  = val;
    WEST:  west_in  = val;
    NORTH: north_in = val;
    SOUTH: south_in = val;
    LOCAL: local_in = val;
    default: local_in = val;  // should never happen
  endcase

  @(posedge clk);
  #1;
  $display("port=%s, in=%b | east_out=%b west_out=%b north_out=%b south_out=%b local_out=%b",
            port.name(), val[36:30],
            east_out[36:30], west_out[36:30], north_out[36:30],
            south_out[36:30], local_out[36:30]);
endtask

initial begin
  // Drive every input to a known value up front
  east_in  = '0;
  west_in  = '0;
  north_in = '0;
  south_in = '0;
  local_in = '0;

  //The location of the testing router
  location = 4'b1010;

  //restarting the module
  rst_n = 0;
  repeat (2) @(posedge clk);  // hold reset across at least one full edge
  rst_n = 1;
  @(posedge clk);
  #1;

  $display(" ");
  $display("Send emptly packages to all inputs at once");
  drive_and_print(EAST, 37'b0000000000000000000000000000000000000);
  drive_and_print(WEST, 37'b0000000000000000000000000000000000000);
  drive_and_print(NORTH, 37'b0000000000000000000000000000000000000);
  drive_and_print(SOUTH, 37'b0000000000000000000000000000000000000);
  drive_and_print(LOCAL, 37'b0000000000000000000000000000000000000);
  $display(" ");

  $display("Send emptly packages to all inputs one by one");
  drive_and_print(EAST, 37'b0000000000000000000000000000000000000);
  @(posedge clk);
  drive_and_print(WEST, 37'b0000000000000000000000000000000000000);
  @(posedge clk);
  drive_and_print(NORTH, 37'b0000000000000000000000000000000000000);
  @(posedge clk);
  drive_and_print(SOUTH, 37'b0000000000000000000000000000000000000);
  @(posedge clk);
  drive_and_print(LOCAL, 37'b0000000000000000000000000000000000000);
  $display(" ");

  $display("Testing all 16 possible headers one by one from local");
  drive_and_print(LOCAL, 37'b1000000000000000000000000000000000000);
  @(posedge clk);
  drive_and_print(LOCAL, 37'b1000100000000000000000000000000000000);
  @(posedge clk);
  drive_and_print(LOCAL, 37'b1001000000000000000000000000000000000);
  @(posedge clk);
  drive_and_print(LOCAL, 37'b1001100000000000000000000000000000000);
  @(posedge clk);
  drive_and_print(LOCAL, 37'b1010000000000000000000000000000000000);
  @(posedge clk);
  drive_and_print(LOCAL, 37'b1010100000000000000000000000000000000);
  @(posedge clk);
  drive_and_print(LOCAL, 37'b1011000000000000000000000000000000000);
  @(posedge clk);
  drive_and_print(LOCAL, 37'b1011100000000000000000000000000000000);
  @(posedge clk);
  drive_and_print(LOCAL, 37'b1100000000000000000000000000000000000);
  @(posedge clk);
  drive_and_print(LOCAL, 37'b1100100000000000000000000000000000000);
  @(posedge clk);
  drive_and_print(LOCAL, 37'b1101000000000000000000000000000000000);
  @(posedge clk);
  drive_and_print(LOCAL, 37'b1101100000000000000000000000000000000);
  @(posedge clk);
  drive_and_print(LOCAL, 37'b1110000000000000000000000000000000000);
  @(posedge clk);
  drive_and_print(LOCAL, 37'b1110100000000000000000000000000000000);
  @(posedge clk);
  drive_and_print(LOCAL, 37'b1111000000000000000000000000000000000);
  @(posedge clk);
  drive_and_print(LOCAL, 37'b1111100000000000000000000000000000000);
  @(posedge clk);
  $display(" ");

  $finish;
end

endmodule

router_tb.vcd
$date
	Tue Aug 25 13:03:45 2026
$end
$version
	Icarus Verilog
$end
$timescale
	1ps
$end
$scope module router_tb $end
$var wire 37 ! west_out [36:0] $end
$var wire 37 " south_out [36:0] $end
$var wire 37 # north_out [36:0] $end
$var wire 37 $ local_out [36:0] $end
$var wire 37 % east_out [36:0] $end
$var reg 1 & clk $end
$var reg 37 ' east_in [36:0] $end
$var reg 37 ( local_in [36:0] $end
$var reg 4 ) location [3:0] $end
$var reg 37 * north_in [36:0] $end
$var reg 1 + rst_n $end
$var reg 37 , south_in [36:0] $end
$var reg 37 - west_in [36:0] $end
$scope module dut $end
$var wire 1 & clk $end
$var wire 37 . east_in [36:0] $end
$var wire 37 / east_out [36:0] $end
$var wire 37 0 local_in [36:0] $end
$var wire 37 1 local_out [36:0] $end
$var wire 4 2 location [3:0] $end
$var wire 37 3 north_in [36:0] $end
$var wire 37 4 north_out [36:0] $end
$var wire 1 + rst_n $end
$var wire 37 5 south_in [36:0] $end
$var wire 37 6 south_out [36:0] $end
$var wire 37 7 west_in [36:0] $end
$var wire 37 8 west_out [36:0] $end
$var reg 37 9 east_reg [36:0] $end
$var reg 37 : local_reg [36:0] $end
$var reg 37 ; north_reg [36:0] $end
$var reg 37 < south_reg [36:0] $end
$var reg 37 = west_reg [36:0] $end
$upscope $end
$scope task drive_and_print $end
$upscope $end
$upscope $end
$enddefinitions $end
$comment Show the parameter values. $end
$dumpall
$end
#0
$dumpvars
bx =
bx <
bx ;
bx :
bx 9
bx 8
b0 7
bx 6
b0 5
bx 4
b0 3
b1010 2
bx 1
b0 0
bx /
b0 .
b0 -
b0 ,
0+
b0 *
b1010 )
b0 (
b0 '
0&
bx %
bx $
bx #
bx "
bx !
$end
#5000
b0 $
b0 1
b0 :
b0 "
b0 6
b0 <
b0 #
b0 4
b0 ;
b0 !
b0 8
b0 =
b0 %
b0 /
b0 9
1&
#10000
0&
#15000
1+
1&
#20000
0&
#25000
1&
#30000
0&
#35000
1&
#40000
0&
#45000
1&
#50000
0&
#55000
1&
#60000
0&
#65000
1&
#70000
0&
#75000
1&
#80000
0&
#85000
1&
#90000
0&
#95000
1&
#100000
0&
#105000
1&
#110000
0&
#115000
1&
#120000
0&
#125000
1&
#130000
0&
#135000
1&
#140000
0&
#145000
1&
#150000
0&
#155000
1&
#160000
0&
#165000
1&
#166000
b1000000000000000000000000000000000000 (
b1000000000000000000000000000000000000 0
#170000
0&
#175000
1&
#180000
0&
#185000
b1000100000000000000000000000000000000 (
b1000100000000000000000000000000000000 0
1&
#190000
0&
#195000
1&
#200000
0&
#205000
b1001000000000000000000000000000000000 (
b1001000000000000000000000000000000000 0
1&
#210000
0&
#215000
1&
#220000
0&
#225000
b1001100000000000000000000000000000000 (
b1001100000000000000000000000000000000 0
1&
#230000
0&
#235000
1&
#240000
0&
#245000
b1010000000000000000000000000000000000 (
b1010000000000000000000000000000000000 0
1&
#250000
0&
#255000
1&
#260000
0&
#265000
b1010100000000000000000000000000000000 (
b1010100000000000000000000000000000000 0
1&
#270000
0&
#275000
b1010100000000000000000000000000000000 !
b1010100000000000000000000000000000000 8
b1010100000000000000000000000000000000 =
1&
#280000
0&
#285000
b1010100000000000000000000000000000000 !
b1010100000000000000000000000000000000 8
b1010100000000000000000000000000000000 =
b1011000000000000000000000000000000000 (
b1011000000000000000000000000000000000 0
1&
#290000
0&
#295000
b0 !
b0 8
b0 =
1&
#300000
0&
#305000
b1011100000000000000000000000000000000 (
b1011100000000000000000000000000000000 0
1&
#310000
0&
#315000
b1011100000000000000000000000000000000 %
b1011100000000000000000000000000000000 /
b1011100000000000000000000000000000000 9
1&
#320000
0&
#325000
b1011100000000000000000000000000000000 %
b1011100000000000000000000000000000000 /
b1011100000000000000000000000000000000 9
b1100000000000000000000000000000000000 (
b1100000000000000000000000000000000000 0
1&
#330000
0&
#335000
b0 %
b0 /
b0 9
1&
#340000
0&
#345000
b1100100000000000000000000000000000000 (
b1100100000000000000000000000000000000 0
1&
#350000
0&
#355000
b1100100000000000000000000000000000000 !
b1100100000000000000000000000000000000 8
b1100100000000000000000000000000000000 =
1&
#360000
0&
#365000
b1100100000000000000000000000000000000 !
b1100100000000000000000000000000000000 8
b1100100000000000000000000000000000000 =
b1101000000000000000000000000000000000 (
b1101000000000000000000000000000000000 0
1&
#370000
0&
#375000
b0 !
b0 8
b0 =
1&
#380000
0&
#385000
b1101100000000000000000000000000000000 (
b1101100000000000000000000000000000000 0
1&
#390000
0&
#395000
b1101100000000000000000000000000000000 %
b1101100000000000000000000000000000000 /
b1101100000000000000000000000000000000 9
1&
#400000
0&
#405000
b1101100000000000000000000000000000000 %
b1101100000000000000000000000000000000 /
b1101100000000000000000000000000000000 9
b1110000000000000000000000000000000000 (
b1110000000000000000000000000000000000 0
1&
#410000
0&
#415000
b0 %
b0 /
b0 9
1&
#420000
0&
#425000
b1110100000000000000000000000000000000 (
b1110100000000000000000000000000000000 0
1&
#430000
0&
#435000
b1110100000000000000000000000000000000 !
b1110100000000000000000000000000000000 8
b1110100000000000000000000000000000000 =
1&
#440000
0&
#445000
b1110100000000000000000000000000000000 !
b1110100000000000000000000000000000000 8
b1110100000000000000000000000000000000 =
b1111000000000000000000000000000000000 (
b1111000000000000000000000000000000000 0
1&
#450000
0&
#455000
b1111000000000000000000000000000000000 #
b1111000000000000000000000000000000000 4
b1111000000000000000000000000000000000 ;
b0 !
b0 8
b0 =
1&
#460000
0&
#465000
b1111000000000000000000000000000000000 #
b1111000000000000000000000000000000000 4
b1111000000000000000000000000000000000 ;
b1111100000000000000000000000000000000 (
b1111100000000000000000000000000000000 0
1&
#470000
0&
#475000
b1111100000000000000000000000000000000 %
b1111100000000000000000000000000000000 /
b1111100000000000000000000000000000000 9
b0 #
b0 4
b0 ;
1&
#480000
0&
#485000
b1111100000000000000000000000000000000 %
b1111100000000000000000000000000000000 /
b1111100000000000000000000000000000000 9
1&
